request_id_helper/__init__.py
request_id_helper/context.py
request_id_helper/helper.py
request_id_helper/logger.py
request_id_helper/version.py
tests/__init__.py
tests/conftest.py
tests/test_helper.py
tests/test_logger.py
request_id_helper-0.2.0.dist-info/LICENSE
request_id_helper-0.2.0.dist-info/METADATA
request_id_helper-0.2.0.dist-info/WHEEL
request_id_helper-0.2.0.dist-info/top_level.txt
request_id_helper-0.2.0.dist-info/RECORD
