Metadata-Version: 2.1
Name: request-id-helper
Version: 0.2.0
Summary: Helper to add request id in logger and context
Home-page: https://github.com/bigbag/request-id-helper
Download-URL: https://pypi.python.org/pypi/request-id-helper
Author: Pavel Liashkov
Author-email: pavel.liashkov@protonmail.com
Maintainer: Pavel Liashkov
Maintainer-email: pavel.liashkov@protonmail.com
License: Apache License, Version 2.0
Platform: POSIX
Classifier: Development Status :: 5 - Production/Stable
Classifier: Programming Language :: Python :: 3 :: Only
Classifier: Programming Language :: Python :: 3.7
Classifier: Programming Language :: Python :: 3.8
Classifier: Programming Language :: Python :: 3.9
Classifier: Programming Language :: Python :: 3.10
Classifier: Programming Language :: Python :: 3.11
Classifier: Programming Language :: Python :: 3.12
Classifier: Programming Language :: Python :: 3.13
Classifier: Operating System :: POSIX
Classifier: Topic :: Software Development
Classifier: Topic :: Software Development :: Libraries
Classifier: Environment :: Console
Classifier: Intended Audience :: Developers
Requires-Python: >=3.7
License-File: LICENSE
